{
  "documents": [
    {
      "name": "projects/droidcon-148cc/databases/(default)/documents/sponsors-nyc-2022/bronze",
      "fields": {
        "displayOrder": {
          "integerValue": "3"
        },
        "sponsors": {
          "arrayValue": {
            "values": [
              {
                "mapValue": {
                  "fields": {
                    "icon": {
                      "stringValue": "https://nyc.droidcon.com/wp-content/uploads/sites/2/2022/06/fanduel.png"
                    },
                    "name": {
                      "stringValue": "FanDuel"
                    },
                    "url": {
                      "stringValue": "https://www.fanduel.com/careers"
                    }
                  }
                }
              },
              {
                "mapValue": {
                  "fields": {
                    "icon": {
                      "stringValue": "https://nyc.droidcon.com/wp-content/uploads/sites/2/2022/05/Vonage.png"
                    },
                    "name": {
                      "stringValue": "Vonage"
                    },
                    "url": {
                      "stringValue": "https://developer.vonage.com/?utm_source=Events&utm_medium=bitly&utm_campaign=Events_Sponsorships_2022&utm_content=DroidconNewYork2022&utm_campaign=2022+Q3+Events&utm_medium=bitly&utm_source=Events"
                    }
                  }
                }
              },
              {
                "mapValue": {
                  "fields": {
                    "url": {
                      "stringValue": "https://tinder.com/"
                    },
                    "icon": {
                      "stringValue": "https://nyc.droidcon.com/wp-content/uploads/sites/2/2022/06/tinder.png"
                    },
                    "name": {
                      "stringValue": "Tinder"
                    }
                  }
                }
              },
              {
                "mapValue": {
                  "fields": {
                    "icon": {
                      "stringValue": "https://nyc.droidcon.com/wp-content/uploads/sites/2/2022/08/embrace.png"
                    },
                    "url": {
                      "stringValue": "https://embrace.io/"
                    },
                    "name": {
                      "stringValue": "Embrace"
                    }
                  }
                }
              },
              {
                "mapValue": {
                  "fields": {
                    "name": {
                      "stringValue": "Amazon Fire TV"
                    },
                    "icon": {
                      "stringValue": "https://nyc.droidcon.com/wp-content/uploads/sites/2/2022/05/Amazonappstore.png"
                    },
                    "url": {
                      "stringValue": "https://developer.amazon.com/apps-and-games"
                    }
                  }
                }
              },
              {
                "mapValue": {
                  "fields": {
                    "name": {
                      "stringValue": "Mobile.dev"
                    },
                    "icon": {
                      "stringValue": "https://nyc.droidcon.com/wp-content/uploads/sites/2/2022/06/mobiledev.png"
                    },
                    "url": {
                      "stringValue": "https://www.mobile.dev/"
                    }
                  }
                }
              },
              {
                "mapValue": {
                  "fields": {
                    "name": {
                      "stringValue": "Gradle"
                    },
                    "icon": {
                      "stringValue": "https://nyc.droidcon.com/wp-content/uploads/sites/2/2022/07/gradle.png"
                    },
                    "url": {
                      "stringValue": "https://gradle.com/"
                    }
                  }
                }
              },
              {
                "mapValue": {
                  "fields": {
                    "url": {
                      "stringValue": "https://www.uber.com/de/en/"
                    },
                    "name": {
                      "stringValue": "Uber"
                    },
                    "icon": {
                      "stringValue": "https://nyc.droidcon.com/wp-content/uploads/sites/2/2022/05/uber-1.png"
                    }
                  }
                }
              },
              {
                "mapValue": {
                  "fields": {
                    "name": {
                      "stringValue": "Product Science"
                    },
                    "icon": {
                      "stringValue": "https://nyc.droidcon.com/wp-content/uploads/sites/2/2022/07/productscience.png"
                    },
                    "url": {
                      "stringValue": "https://www.productscience.ai/"
                    }
                  }
                }
              },
              {
                "mapValue": {
                  "fields": {
                    "url": {
                      "stringValue": "https://www.zillow.com/careers/"
                    },
                    "name": {
                      "stringValue": "Zillow"
                    },
                    "icon": {
                      "stringValue": "https://nyc.droidcon.com/wp-content/uploads/sites/2/2022/07/zillow.png"
                    }
                  }
                }
              },
              {
                "mapValue": {
                  "fields": {
                    "name": {
                      "stringValue": "NY Times"
                    },
                    "url": {
                      "stringValue": "https://www.nytimes.com/"
                    },
                    "icon": {
                      "stringValue": "https://nyc.droidcon.com/wp-content/uploads/sites/2/2022/08/ny-times.png"
                    }
                  }
                }
              },
              {
                "mapValue": {
                  "fields": {
                    "name": {
                      "stringValue": "Runway"
                    },
                    "icon": {
                      "stringValue": "https://nyc.droidcon.com/wp-content/uploads/sites/2/2022/08/runway.png"
                    },
                    "url": {
                      "stringValue": "https://www.runway.team/"
                    }
                  }
                }
              },
              {
                "mapValue": {
                  "fields": {
                    "name": {
                      "stringValue": "TikTok"
                    },
                    "url": {
                      "stringValue": "https://www.tiktok.com/"
                    },
                    "icon": {
                      "stringValue": "https://nyc.droidcon.com/wp-content/uploads/sites/2/2022/08/tiktok.png"
                    }
                  }
                }
              },
              {
                "mapValue": {
                  "fields": {
                    "name": {
                      "stringValue": "Emerge Tools"
                    },
                    "icon": {
                      "stringValue": "https://nyc.droidcon.com/wp-content/uploads/sites/2/2022/08/emerge.png"
                    },
                    "url": {
                      "stringValue": "https://www.emergetools.com/"
                    }
                  }
                }
              },
              {
                "mapValue": {
                  "fields": {
                    "url": {
                      "stringValue": "https://www.mindbodyonline.com/"
                    },
                    "name": {
                      "stringValue": "ClassPass"
                    },
                    "icon": {
                      "stringValue": "https://nyc.droidcon.com/wp-content/uploads/sites/2/2022/08/mindbody.png"
                    }
                  }
                }
              },
              {
                "mapValue": {
                  "fields": {
                    "name": {
                      "stringValue": "Peloton"
                    },
                    "icon": {
                      "stringValue": "https://nyc.droidcon.com/wp-content/uploads/sites/2/2022/08/peleton.png"
                    },
                    "url": {
                      "stringValue": "https://www.onepeloton.com/careers/software"
                    }
                  }
                }
              }
            ]
          }
        }
      },
      "createTime": "2022-07-28T13:25:48.713370Z",
      "updateTime": "2022-08-24T22:24:01.164831Z"
    },
    {
      "name": "projects/droidcon-148cc/databases/(default)/documents/sponsors-nyc-2022/community partner",
      "fields": {
        "displayOrder": {
          "integerValue": "5"
        },
        "sponsors": {
          "arrayValue": {
            "values": [
              {
                "mapValue": {
                  "fields": {
                    "icon": {
                      "stringValue": "https://nyc.droidcon.com/wp-content/uploads/sites/2/2022/05/Sticker-Mule.png"
                    },
                    "url": {
                      "stringValue": "https://www.stickermule.com/custom-stickers?utm_source=google&utm_campaign=droidconny22&utm_id=droidconny22"
                    },
                    "name": {
                      "stringValue": "Stickermule"
                    }
                  }
                }
              },
              {
                "mapValue": {
                  "fields": {
                    "name": {
                      "stringValue": "GDG NY"
                    },
                    "url": {
                      "stringValue": "https://gdg.community.dev/gdg-nyc/"
                    },
                    "icon": {
                      "stringValue": "https://nyc.droidcon.com/wp-content/uploads/sites/2/2022/08/gdg.jpeg"
                    }
                  }
                }
              },
              {
                "mapValue": {
                  "fields": {
                    "icon": {
                      "stringValue": "https://nyc.droidcon.com/wp-content/uploads/sites/2/2022/08/1647596820898.jpeg"
                    },
                    "name": {
                      "stringValue": "Groundbreaker"
                    },
                    "url": {
                      "stringValue": "https://groundbreaker.org/"
                    }
                  }
                }
              }
            ]
          }
        }
      },
      "createTime": "2022-07-28T13:43:12.750981Z",
      "updateTime": "2022-08-24T15:31:44.288938Z"
    },
    {
      "name": "projects/droidcon-148cc/databases/(default)/documents/sponsors-nyc-2022/gold",
      "fields": {
        "prominent": {
          "booleanValue": true
        },
        "displayOrder": {
          "integerValue": "1"
        },
        "sponsors": {
          "arrayValue": {
            "values": [
              {
                "mapValue": {
                  "fields": {
                    "name": {
                      "stringValue": "Waldo"
                    },
                    "icon": {
                      "stringValue": "https://nyc.droidcon.com/wp-content/uploads/sites/2/2022/06/waldo.png"
                    },
                    "url": {
                      "stringValue": "https://www.waldo.com/"
                    }
                  }
                }
              },
              {
                "mapValue": {
                  "fields": {
                    "name": {
                      "stringValue": "Microsoft Surface Duo"
                    },
                    "icon": {
                      "stringValue": "https://nyc.droidcon.com/wp-content/uploads/sites/2/2022/05/microsoft-surface-duo.png"
                    },
                    "url": {
                      "stringValue": "https://docs.microsoft.com/en-gb/dual-screen/"
                    }
                  }
                }
              },
              {
                "mapValue": {
                  "fields": {
                    "icon": {
                      "stringValue": "https://nyc.droidcon.com/wp-content/uploads/sites/2/2022/05/Touchlab-1.png"
                    },
                    "name": {
                      "stringValue": "Touchlab"
                    },
                    "url": {
                      "stringValue": "https://touchlab.co/"
                    }
                  }
                }
              }
            ]
          }
        }
      },
      "createTime": "2022-07-28T13:26:35.105699Z",
      "updateTime": "2022-08-24T15:39:35.458978Z"
    },
    {
      "name": "projects/droidcon-148cc/databases/(default)/documents/sponsors-nyc-2022/lanyard",
      "fields": {
        "displayOrder": {
          "integerValue": "7"
        },
        "sponsors": {
          "arrayValue": {
            "values": [
              {
                "mapValue": {
                  "fields": {
                    "name": {
                      "stringValue": "Stream"
                    },
                    "url": {
                      "stringValue": "https://getstream.io/"
                    },
                    "icon": {
                      "stringValue": "https://nyc.droidcon.com/wp-content/uploads/sites/2/2022/05/Stream.png"
                    }
                  }
                }
              }
            ]
          }
        }
      },
      "createTime": "2022-08-08T11:29:54.988569Z",
      "updateTime": "2022-08-24T15:41:02.986968Z"
    },
    {
      "name": "projects/droidcon-148cc/databases/(default)/documents/sponsors-nyc-2022/platinum",
      "fields": {
        "displayOrder": {
          "integerValue": "0"
        },
        "sponsors": {
          "arrayValue": {
            "values": [
            ]
          }
        }
      },
      "createTime": "2022-07-28T13:26:17.814742Z",
      "updateTime": "2022-08-08T11:27:16.881081Z"
    },
    {
      "name": "projects/droidcon-148cc/databases/(default)/documents/sponsors-nyc-2022/silver",
      "fields": {
        "displayOrder": {
          "integerValue": "2"
        },
        "sponsors": {
          "arrayValue": {
            "values": [
              {
                "mapValue": {
                  "fields": {
                    "name": {
                      "stringValue": "Couchbase"
                    },
                    "icon": {
                      "stringValue": "https://nyc.droidcon.com/wp-content/uploads/sites/2/2022/06/couchbase-1.png"
                    },
                    "url": {
                      "stringValue": "https://www.couchbase.com"
                    }
                  }
                }
              },
              {
                "mapValue": {
                  "fields": {
                    "url": {
                      "stringValue": "https://www.instabug.com/"
                    },
                    "icon": {
                      "stringValue": "https://nyc.droidcon.com/wp-content/uploads/sites/2/2022/06/Instabug.png"
                    },
                    "name": {
                      "stringValue": "Instabug"
                    }
                  }
                }
              },
              {
                "mapValue": {
                  "fields": {
                    "name": {
                      "stringValue": "Bitrise"
                    },
                    "icon": {
                      "stringValue": "https://nyc.droidcon.com/wp-content/uploads/sites/2/2022/05/bitrise.png"
                    },
                    "url": {
                      "stringValue": "https://www.bitrise.io/why/technologies/android-continuous-integration"
                    }
                  }
                }
              }
            ]
          }
        }
      },
      "createTime": "2022-07-28T13:26:45.418516Z",
      "updateTime": "2022-08-24T22:19:07.869486Z"
    },
    {
      "name": "projects/droidcon-148cc/databases/(default)/documents/sponsors-nyc-2022/video",
      "fields": {
        "displayOrder": {
          "integerValue": "4"
        },
        "sponsors": {
          "arrayValue": {
            "values": [
              {
                "mapValue": {
                  "fields": {
                    "url": {
                      "stringValue": "https://www.americanexpress.com/en-us/careers/career-areas/technology/"
                    },
                    "icon": {
                      "stringValue": "https://nyc.droidcon.com/wp-content/uploads/sites/2/2022/08/AMEX.png"
                    },
                    "name": {
                      "stringValue": "AMEX"
                    }
                  }
                }
              }
            ]
          }
        }
      },
      "createTime": "2022-07-28T13:42:58.957284Z",
      "updateTime": "2022-08-24T22:21:44.337764Z"
    }
  ]
}
